hicreppy/__init__.py
hicreppy/__main__.py
hicreppy/hicrep.py
hicreppy/cli/__init__.py
hicreppy/utils/__init__.py
hicreppy/utils/mat_process.py
tests/__init__.py
tests/test_cli.py
tests/test_hicrep.py
tests/test_mat_process.py
hicreppy-0.1.0.dist-info/LICENSE
hicreppy-0.1.0.dist-info/METADATA
hicreppy-0.1.0.dist-info/WHEEL
hicreppy-0.1.0.dist-info/entry_points.txt
hicreppy-0.1.0.dist-info/top_level.txt
hicreppy-0.1.0.dist-info/RECORD
