Metadata-Version: 2.1
Name: hicreppy
Version: 0.1.0
Summary: Reimplementation of the hicrep with added support for sparse matrix and multiple chromosomes.
Home-page: https://github.com/cmdoret/hicreppy
Author: cmdoret
Author-email: cyril.matthey-doret@pasteur.fr
License: GPLv2
Platform: UNKNOWN
Classifier: Development Status :: 3 - Alpha
Classifier: Intended Audience :: Science/Research
Classifier: Intended Audience :: Science/Research
Classifier: License :: OSI Approved :: GNU General Public License v2 (GPLv2)
Classifier: Programming Language :: Python
Classifier: Programming Language :: Python :: 3
Classifier: Programming Language :: Python :: 3 :: Only
Classifier: Programming Language :: Python :: 3.6
Classifier: Programming Language :: Python :: 3.7
Classifier: Topic :: Scientific/Engineering
Classifier: Topic :: Scientific/Engineering :: Bio-Informatics
Classifier: Operating System :: Microsoft :: Windows
Classifier: Operating System :: POSIX
Classifier: Operating System :: Unix
Classifier: Operating System :: MacOS
Requires-Python: >=3.6
License-File: LICENSE
Requires-Dist: click
Requires-Dist: cooler
Requires-Dist: numpy
Requires-Dist: pandas
Requires-Dist: scipy
